{"UAc7kepzJPkrSn4uqTRvmw==":"background4.jpg","dceJdXrpZt10ONTCMBZwaQ==":"intro-1753x873.jpg","Vb3OskX71amYOCXZZKarEg==":"logo-192x76.png","4uKpfhAWFLmzfwlSOA+uOA==":"intro-1753x873.jpeg","QgGVsM/ujKKHr7NV5jCO1w==":"perro-intro-1920x1280.jpg","HiyM3YbcDEfJSe70goRyTQ==":"perro-intro-1920x1280.jpeg","kbvOX/rOlOvaB0/Je0Y5dQ==":"perro-intro-1-1920x1280.jpeg","EtqbKn3mly6KeaBiQ0lnWQ==":"salchichaygato-1240x744.jpg","WrYoWNjPvVtLDcBopQYXTQ==":"dos-perros-1450x900.jpg","dy+s6caiIbmtAFNUzzYyyQ==":"dos-perros-1450x900.jpeg","fA5jmgsgZfMvCZl1Cj4blg==":"chapi-1000x500.jpg","SRMb9xRLJAU/YmCt9TJ/FA==":"gatito-1298x649.jpg","iVQLRJ6HMsCtmQovC+yDpA==":"gatito2-1280x800.jpg","C6ZTJN2zy6h1nr6kPps+Gw==":"gatito2-1280x800.jpeg","YYu0Qv3tIDNy2qEGBwiK9g==":"perro-gato-2000x1333.jpg","XBxvTkVoamiJEF7MYlXetQ==":"perro-gato-2000x1333.jpeg","CymYTm3W5L52Y02pS4B/MA==":"perro-y-persona-1200x821.jpg","oKd8++U3shvsLfm6b37pUg==":"perro-y-persona-1200x821.jpeg","JDn8wLfGoaSabJb4x/7ZoA==":"abrazando-perros-1024x679.jpg"}